pyephember/__init__.py
pyephember/pyephember.py
pyephember-0.4.1.dist-info/LICENSE.txt
pyephember-0.4.1.dist-info/METADATA
pyephember-0.4.1.dist-info/WHEEL
pyephember-0.4.1.dist-info/top_level.txt
pyephember-0.4.1.dist-info/RECORD
