Metadata-Version: 2.2
Name: pyephember
Version: 0.4.1
Summary: Python library to work with ember from EPH Controls
Home-page: https://github.com/ttroy50/pyephember
Download-URL: https://github.com/ttroy50/pyephember/archive/0.4.0.tar.gz
Author: Thom Troy
Author-email: ttroy50@gmail.com
License: MIT
Keywords: eph ember
Platform: any
License-File: LICENSE.txt
Requires-Dist: requests
Requires-Dist: paho-mqtt
Dynamic: author
Dynamic: author-email
Dynamic: download-url
Dynamic: home-page
Dynamic: keywords
Dynamic: license
Dynamic: platform
Dynamic: requires-dist
Dynamic: summary
